adafruit_ble/__init__.py
adafruit_ble/advertising/__init__.py
adafruit_ble/advertising/adafruit.py
adafruit_ble/advertising/standard.py
adafruit_ble/attributes/__init__.py
adafruit_ble/characteristics/__init__.py
adafruit_ble/characteristics/float.py
adafruit_ble/characteristics/int.py
adafruit_ble/characteristics/json.py
adafruit_ble/characteristics/stream.py
adafruit_ble/characteristics/string.py
adafruit_ble/services/__init__.py
adafruit_ble/services/circuitpython.py
adafruit_ble/services/microbit.py
adafruit_ble/services/nordic.py
adafruit_ble/services/sphero.py
adafruit_ble/services/standard/__init__.py
adafruit_ble/services/standard/device_info.py
adafruit_ble/services/standard/hid.py
adafruit_ble/uuid/__init__.py
adafruit_circuitpython_ble-10.0.15.dist-info/licenses/LICENSE
adafruit_circuitpython_ble-10.0.15.dist-info/METADATA
adafruit_circuitpython_ble-10.0.15.dist-info/WHEEL
adafruit_circuitpython_ble-10.0.15.dist-info/top_level.txt
adafruit_circuitpython_ble-10.0.15.dist-info/RECORD
