Metadata-Version: 2.4
Name: adafruit-circuitpython-ble
Version: 10.0.15
Summary: Bluetooth Low Energy (BLE) library for CircuitPython
Author-email: Adafruit Industries <circuitpython@adafruit.com>
License: MIT
Project-URL: Homepage, https://github.com/adafruit/Adafruit_CircuitPython_BLE
Keywords: adafruit,blinka,circuitpython,micropython,ble,bluetooth
Classifier: Intended Audience :: Developers
Classifier: Topic :: Software Development :: Libraries
Classifier: Topic :: Software Development :: Embedded Systems
Classifier: Topic :: System :: Hardware
Classifier: License :: OSI Approved :: MIT License
Classifier: Programming Language :: Python :: 3
License-File: LICENSE
Requires-Dist: Adafruit-Blinka
Requires-Dist: adafruit-blinka-bleio
Requires-Dist: adafruit-circuitpython-typing
Requires-Dist: typing-extensions~=4.0.0
Provides-Extra: optional
Dynamic: license-file
